tlt/__init__.py
tlt/data/__init__.py
tlt/data/dataset.py
tlt/data/label_transforms_factory.py
tlt/data/loader.py
tlt/data/mixup.py
tlt/data/random_augment_label.py
tlt/loss/__init__.py
tlt/loss/cross_entropy.py
tlt/models/__init__.py
tlt/models/layers.py
tlt/models/lvvit.py
tlt/utils/__init__.py
tlt/utils/utils.py
tlt-0.2.0.dist-info/LICENSE
tlt-0.2.0.dist-info/METADATA
tlt-0.2.0.dist-info/WHEEL
tlt-0.2.0.dist-info/top_level.txt
tlt-0.2.0.dist-info/RECORD
